{
    "array":[
        {"name":"Afghanistan","json":"AFG"},{"name":"Angola","json":"AGO"},{"name":"Albania","json":"ALB"},{"name":"United Arab Emirates","json":"ARE"},{"name":"Argentina","json":"ARG"},{"name":"Armenia","json":"ARM"},{"name":"Antarctica","json":"ATA"},{"name":"French Southern and Antarctic Lands","json":"ATF"},{"name":"Australia","json":"AUS"},{"name":"Austria","json":"AUT"},{"name":"Azerbaijan","json":"AZE"},{"name":"Burundi","json":"BDI"},{"name":"Belgium","json":"BEL"},{"name":"Benin","json":"BEN"},{"name":"Burkina Faso","json":"BFA"},{"name":"Bangladesh","json":"BGD"},{"name":"Bulgaria","json":"BGR"},{"name":"The Bahamas","json":"BHS"},{"name":"Bosnia and Herzegovina","json":"BIH"},{"name":"Belarus","json":"BLR"},{"name":"Belize","json":"BLZ"},{"name":"Bermuda","json":"BMU"},{"name":"Bolivia","json":"BOL"},{"name":"Brazil","json":"BRA"},{"name":"Brunei","json":"BRN"},{"name":"Bhutan","json":"BTN"},{"name":"Botswana","json":"BWA"},{"name":"Central African Republic","json":"CAF"},{"name":"Canada","json":"CAN"},{"name":"Switzerland","json":"CHE"},{"name":"Chile","json":"CHL"},{"name":"China","json":"CHN"},{"name":"Ivory Coast","json":"CIV"},{"name":"Cameroon","json":"CMR"},{"name":"Democratic Republic of the Congo","json":"COD"},{"name":"Republic of the Congo","json":"COG"},{"name":"Colombia","json":"COL"},{"name":"Costa Rica","json":"CRI"},{"name":"Cuba","json":"CUB"},{"name":"Northern Cyprus","json":"-99"},{"name":"Cyprus","json":"CYP"},{"name":"Czech Republic","json":"CZE"},{"name":"Germany","json":"DEU"},{"name":"Djibouti","json":"DJI"},{"name":"Denmark","json":"DNK"},{"name":"Dominican Republic","json":"DOM"},{"name":"Algeria","json":"DZA"},{"name":"Ecuador","json":"ECU"},{"name":"Egypt","json":"EGY"},{"name":"Eritrea","json":"ERI"},{"name":"Spain","json":"ESP"},{"name":"Estonia","json":"EST"},{"name":"Ethiopia","json":"ETH"},{"name":"Finland","json":"FIN"},{"name":"Fiji","json":"FJI"},{"name":"Falkland Islands","json":"FLK"},{"name":"France","json":"FRA"},{"name":"Gabon","json":"GAB"},{"name":"United Kingdom","json":"GBR"},{"name":"Georgia","json":"GEO"},{"name":"Ghana","json":"GHA"},{"name":"Guinea","json":"GIN"},{"name":"Gambia","json":"GMB"},{"name":"Guinea Bissau","json":"GNB"},{"name":"Equatorial Guinea","json":"GNQ"},{"name":"Greece","json":"GRC"},{"name":"Greenland","json":"GRL"},{"name":"Guatemala","json":"GTM"},{"name":"French Guiana","json":"GUF"},{"name":"Guyana","json":"GUY"},{"name":"Honduras","json":"HND"},{"name":"Croatia","json":"HRV"},{"name":"Haiti","json":"HTI"},{"name":"Hungary","json":"HUN"},{"name":"Indonesia","json":"IDN"},{"name":"India","json":"IND"},{"name":"Ireland","json":"IRL"},{"name":"Iran","json":"IRN"},{"name":"Iraq","json":"IRQ"},{"name":"Iceland","json":"ISL"},{"name":"Israel","json":"ISR"},{"name":"Italy","json":"ITA"},{"name":"Jamaica","json":"JAM"},{"name":"Jordan","json":"JOR"},{"name":"Japan","json":"JPN"},{"name":"Kazakhstan","json":"KAZ"},{"name":"Kenya","json":"KEN"},{"name":"Kyrgyzstan","json":"KGZ"},{"name":"Cambodia","json":"KHM"},{"name":"South Korea","json":"KOR"},{"name":"Kosovo","json":"CS-KM"},{"name":"Kuwait","json":"KWT"},{"name":"Laos","json":"LAO"},{"name":"Lebanon","json":"LBN"},{"name":"Liberia","json":"LBR"},{"name":"Libya","json":"LBY"},{"name":"Sri Lanka","json":"LKA"},{"name":"Lesotho","json":"LSO"},{"name":"Lithuania","json":"LTU"},{"name":"Luxembourg","json":"LUX"},{"name":"Latvia","json":"LVA"},{"name":"Morocco","json":"MAR"},{"name":"Moldova","json":"MDA"},{"name":"Madagascar","json":"MDG"},{"name":"Mexico","json":"MEX"},{"name":"Macedonia","json":"MKD"},{"name":"Mali","json":"MLI"},{"name":"Malta","json":"MLT"},{"name":"Myanmar","json":"MMR"},{"name":"Montenegro","json":"MNE"},{"name":"Mongolia","json":"MNG"},{"name":"Mozambique","json":"MOZ"},{"name":"Mauritania","json":"MRT"},{"name":"Malawi","json":"MWI"},{"name":"Malaysia","json":"MYS"},{"name":"Namibia","json":"NAM"},{"name":"New Caledonia","json":"NCL"},{"name":"Niger","json":"NER"},{"name":"Nigeria","json":"NGA"},{"name":"Nicaragua","json":"NIC"},{"name":"Netherlands","json":"NLD"},{"name":"Norway","json":"NOR"},{"name":"Nepal","json":"NPL"},{"name":"New Zealand","json":"NZL"},{"name":"Oman","json":"OMN"},{"name":"Pakistan","json":"PAK"},{"name":"Panama","json":"PAN"},{"name":"Peru","json":"PER"},{"name":"Philippines","json":"PHL"},{"name":"Papua New Guinea","json":"PNG"},{"name":"Poland","json":"POL"},{"name":"Puerto Rico","json":"PRI"},{"name":"North Korea","json":"PRK"},{"name":"Portugal","json":"PRT"},{"name":"Paraguay","json":"PRY"},{"name":"Qatar","json":"QAT"},{"name":"Romania","json":"ROU"},{"name":"Russia","json":"RUS"},{"name":"Rwanda","json":"RWA"},{"name":"Western Sahara","json":"ESH"},{"name":"Saudi Arabia","json":"SAU"},{"name":"Sudan","json":"SDN"},{"name":"South Sudan","json":"SSD"},{"name":"Senegal","json":"SEN"},{"name":"Solomon Islands","json":"SLB"},{"name":"Sierra Leone","json":"SLE"},{"name":"El Salvador","json":"SLV"},{"name":"Somaliland","json":"-99"},{"name":"Somalia","json":"SOM"},{"name":"Republic of Serbia","json":"SRB"},{"name":"Suriname","json":"SUR"},{"name":"Slovakia","json":"SVK"},{"name":"Slovenia","json":"SVN"},{"name":"Sweden","json":"SWE"},{"name":"Swaziland","json":"SWZ"},{"name":"Syria","json":"SYR"},{"name":"Chad","json":"TCD"},{"name":"Togo","json":"TGO"},{"name":"Thailand","json":"THA"},{"name":"Tajikistan","json":"TJK"},{"name":"Turkmenistan","json":"TKM"},{"name":"East Timor","json":"TLS"},{"name":"Trinidad and Tobago","json":"TTO"},{"name":"Tunisia","json":"TUN"},{"name":"Turkey","json":"TUR"},{"name":"Taiwan","json":"TWN"},{"name":"United Republic of Tanzania","json":"TZA"},{"name":"Uganda","json":"UGA"},{"name":"Ukraine","json":"UKR"},{"name":"Uruguay","json":"URY"},{"name":"United States of America","json":"USA"},{"name":"Uzbekistan","json":"UZB"},{"name":"Venezuela","json":"VEN"},{"name":"Vietnam","json":"VNM"},{"name":"Vanuatu","json":"VUT"},{"name":"West Bank","json":"PSE"},{"name":"Yemen","json":"YEM"},{"name":"South Africa","json":"ZAF"},{"name":"Zambia","json":"ZMB"},{"name":"Zimbabwe","json":"ZWE"}

    ]
}